LICENSE
MANIFEST.in
README.md
README.rst
pyproject.toml
setup.cfg
setup.py
src/engineio/__init__.py
src/engineio/asyncio_client.py
src/engineio/asyncio_server.py
src/engineio/asyncio_socket.py
src/engineio/client.py
src/engineio/exceptions.py
src/engineio/json.py
src/engineio/middleware.py
src/engineio/packet.py
src/engineio/payload.py
src/engineio/server.py
src/engineio/socket.py
src/engineio/static_files.py
src/engineio/async_drivers/__init__.py
src/engineio/async_drivers/aiohttp.py
src/engineio/async_drivers/asgi.py
src/engineio/async_drivers/eventlet.py
src/engineio/async_drivers/gevent.py
src/engineio/async_drivers/gevent_uwsgi.py
src/engineio/async_drivers/sanic.py
src/engineio/async_drivers/threading.py
src/engineio/async_drivers/tornado.py
src/python_engineio_yas.egg-info/PKG-INFO
src/python_engineio_yas.egg-info/SOURCES.txt
src/python_engineio_yas.egg-info/dependency_links.txt
src/python_engineio_yas.egg-info/not-zip-safe
src/python_engineio_yas.egg-info/requires.txt
src/python_engineio_yas.egg-info/top_level.txt