Metadata-Version: 2.1
Name: python-engineio-yas
Version: 4.3.2.dev0
Summary: Engine.IO server and client for Python
Home-page: https://github.com/HoomanRadmehr/python-engineio.git
Author: HoomanRadmehr
Author-email: hooman.radmehr.dev@gmail.com
License: UNKNOWN
Platform: UNKNOWN
Classifier: Environment :: Web Environment
Classifier: Intended Audience :: Developers
Classifier: Programming Language :: Python :: 3
Classifier: License :: OSI Approved :: MIT License
Classifier: Operating System :: OS Independent
Requires-Python: >=3.6
Provides-Extra: asyncio_client
Provides-Extra: client
